action/__init__.py
action/action.py
examplepip-1.1.dist-info/METADATA
examplepip-1.1.dist-info/RECORD
examplepip-1.1.dist-info/WHEEL
examplepip-1.1.dist-info/top_level.txt
