Metadata-Version: 2.1
Name: examplepip
Version: 1.1
Summary: Example pip package
Home-page: UNKNOWN
Author: Vikram-Action
Author-email: UNKNOWN
License: UNKNOWN
Platform: UNKNOWN
